timg/__init__.py
timg/__main__.py
timg/argparser.py
timg/meta.py
timg/renderer.py
timg/methods/__init__.py
timg/methods/ansi.py
timg/methods/ansi_methods.py
timg/methods/ascii.py
timg/methods/method.py
timg/methods/sixel.py
timg-1.1.6.dist-info/LICENSE
timg-1.1.6.dist-info/METADATA
timg-1.1.6.dist-info/WHEEL
timg-1.1.6.dist-info/entry_points.txt
timg-1.1.6.dist-info/top_level.txt
timg-1.1.6.dist-info/RECORD
