Metadata-Version: 2.1
Name: timg
Version: 1.1.6
Summary: print an image in terminal
Home-page: https://github.com/adzierzanowski/timg
Author: Aleksander Dzierżanowski
Author-email: a.dzierzanowski1@gmail.com
License: MIT
Platform: UNKNOWN
Classifier: Development Status :: 5 - Production/Stable
Classifier: Environment :: Console
Classifier: Intended Audience :: End Users/Desktop
Classifier: License :: OSI Approved :: MIT License
Classifier: Operating System :: OS Independent
Classifier: Programming Language :: Python :: 3
Classifier: Topic :: Multimedia :: Graphics :: Viewers
Requires-Dist: pillow
